interactor/__init__.py
interactor/addon.py
interactor/errors.py
interactor/options.py
interactor/server.py
interactor/zeroconf.py
interactor/commander/__init__.py
interactor/commander/animations.py
interactor/commander/devices.py
interactor/commander/errors.py
interactor/commander/helpers.py
interactor/commander/selector.py
interactor/commander/store.py
interactor/commander/commands/__init__.py
interactor/commander/commands/animations.py
interactor/commander/commands/clean.py
interactor/commander/commands/control.py
interactor/commander/commands/discover.py
interactor/commander/commands/effects.py
interactor/commander/commands/help.py
interactor/commander/commands/legacy.py
interactor/commander/commands/scenes.py
interactor/commander/commands/sio.py
interactor/commander/commands/status.py
interactor/database/__init__.py
interactor/database/base.py
interactor/database/database.py
interactor/database/query.py
interactor/database/migrations/script.py.mako
interactor/database/migrations/versions/119f5f1434f7_add_scenes.py
interactor/database/migrations/versions/aab549c5cdbd_add_scene_info.py
interactor/database/models/__init__.py
interactor/database/models/scene.py
interactor/database/models/scene_info.py
interactor/database/models/scene_spec.py
interactor_webapp/interactor/build/favicon.png
interactor_webapp/interactor/build/index.html
interactor_webapp/interactor/build/_app/env.js
interactor_webapp/interactor/build/_app/version.json
interactor_webapp/interactor/build/_app/immutable/chunks/entry.T_kPiorR.js
interactor_webapp/interactor/build/_app/immutable/chunks/index.CIIC7OpS.js
interactor_webapp/interactor/build/_app/immutable/chunks/index.HBdRwm6d.js
interactor_webapp/interactor/build/_app/immutable/chunks/scheduler.BRlKLB1Y.js
interactor_webapp/interactor/build/_app/immutable/entry/app.NzH2qvRA.js
interactor_webapp/interactor/build/_app/immutable/entry/start.DP0uoXht.js
interactor_webapp/interactor/build/_app/immutable/nodes/0.kUf9z7Bw.js
lifx_photons_interactor-0.16.11.dist-info/METADATA
lifx_photons_interactor-0.16.11.dist-info/WHEEL
lifx_photons_interactor-0.16.11.dist-info/entry_points.txt
lifx_photons_interactor-0.16.11.dist-info/RECORD
