Metadata-Version: 2.4
Name: lifx-photons-interactor
Version: 0.16.11
Summary: A server for interacting with LIFX lights over the LAN
Project-URL: Homepage, https://photons.delfick.com/apps/interactor/
Author-email: Stephen Moore <github@delfick.com>
License-Expression: MIT
Keywords: lifx,photons
Requires-Python: >=3.12
Requires-Dist: aiosqlite==0.17.0
Requires-Dist: alembic==1.13.1
Requires-Dist: lifx-photons-core[web-server]>=0.46.6
Requires-Dist: netifaces==0.11.0
Requires-Dist: sqlalchemy[asyncio]==2.0.36
Requires-Dist: zeroconf==0.36.12
